datagovsg_api/__init__.py
datagovsg_api/datagovsg.py
datagovsg_api/environment.py
datagovsg_api/tests.py
datagovsg_api/transport.py
datagovsg_api-0.1.0.dist-info/DESCRIPTION.rst
datagovsg_api-0.1.0.dist-info/METADATA
datagovsg_api-0.1.0.dist-info/RECORD
datagovsg_api-0.1.0.dist-info/WHEEL
datagovsg_api-0.1.0.dist-info/metadata.json
datagovsg_api-0.1.0.dist-info/top_level.txt
