Metadata-Version: 2.0
Name: datagovsg-api
Version: 0.1.0
Summary: Unofficial API wrapper for developers.data.gov.sg
Home-page: https://github.com/half0wl/datagovsg_api
Author: Ray Chen
Author-email: ray@half0wl.com
License: MIT
Keywords: data.gov.sg sgdata singapore
Platform: UNKNOWN
Classifier: Intended Audience :: Developers
Classifier: License :: OSI Approved :: MIT License
Classifier: Programming Language :: Python :: 2.7
Classifier: Programming Language :: Python :: 3.3
Classifier: Programming Language :: Python :: 3.4
Classifier: Programming Language :: Python :: 3.5
Classifier: Programming Language :: Python :: 3.6
Classifier: Topic :: Software Development :: Libraries
Requires-Dist: requests (>=2.13.0)
